pylineclip/__init__.py
pylineclip-0.9.1.data/scripts/DemoLineclip.py
pylineclip-0.9.1.dist-info/METADATA
pylineclip-0.9.1.dist-info/RECORD
pylineclip-0.9.1.dist-info/WHEEL
pylineclip-0.9.1.dist-info/top_level.txt
